README.txt
setup.py
inquant/__init__.py
inquant/tools/__init__.py
inquant/tools/mkvimproject/__init__.py
inquant/tools/mkvimproject/mkvimproject.py
inquant/tools/mkvimproject/project.py
mkvimproject.egg-info/PKG-INFO
mkvimproject.egg-info/SOURCES.txt
mkvimproject.egg-info/dependency_links.txt
mkvimproject.egg-info/entry_points.txt
mkvimproject.egg-info/namespace_packages.txt
mkvimproject.egg-info/not-zip-safe
mkvimproject.egg-info/top_level.txt
