Metadata-Version: 1.0
Name: mkvimproject
Version: 0.4.2.1
Summary: Create a VIM Project file
Home-page: http://www.eletztrick.de/software
Author: Stefan Eletzhofer
Author-email: stefan.eletzhofer@inquant.de
License: GPL
Keywords: vim project development tool python
Platform: UNKNOWN
Classifier: Programming Language :: Python
Classifier: Topic :: Software Development :: Libraries :: Python Modules
Classifier: Topic :: Software Development :: Build Tools
Classifier: Topic :: Text Editors :: Integrated Development Environments (IDE)
